cradle_app/__init__.py
cradle_app/main.py
cradle_app-0.1.1.dist-info/entry_points.txt
cradle_app-0.1.1.dist-info/WHEEL
cradle_app-0.1.1.dist-info/METADATA
cradle_app-0.1.1.dist-info/RECORD
