Metadata-Version: 2.1
Name: cradle-app
Version: 0.1.1
Summary: Test ML models in production (or otherwise)
Author: swiftdiaries
Author-email: adhita94@gmail.com
Requires-Python: >=3.8,<4.0
Classifier: Programming Language :: Python :: 3
Classifier: Programming Language :: Python :: 3.8
Requires-Dist: black (>=19.10b0,<20.0)
Requires-Dist: fastapi[all] (>=0.59.0,<0.60.0)
Requires-Dist: gradio (>=1.0.0,<2.0.0)
Requires-Dist: pre-commit (>=2.6.0,<3.0.0)
Requires-Dist: typer[all] (>=0.3.0,<0.4.0)
